protocolimplementsdecorator/__init__.py
protocolimplementsdecorator/implements.py
protocolimplementsdecorator/py.typed
Protocol_Implements_Decorator-1.1.4.dist-info/LICENSE
Protocol_Implements_Decorator-1.1.4.dist-info/METADATA
Protocol_Implements_Decorator-1.1.4.dist-info/WHEEL
Protocol_Implements_Decorator-1.1.4.dist-info/top_level.txt
Protocol_Implements_Decorator-1.1.4.dist-info/RECORD
